myocr/__init__.py
myocr/__main__.py
myocr/base.py
myocr/config.py
myocr/py.typed
myocr/types.py
myocr/utils.py
myocr/version.py
myocr/extractor/__init__.py
myocr/extractor/base.py
myocr/extractor/chat_extractor.py
myocr/modeling/__init__.py
myocr/modeling/activation.py
myocr/modeling/model.py
myocr/modeling/utils.py
myocr/modeling/architectures/__init__.py
myocr/modeling/architectures/base_model.py
myocr/modeling/backbones/__init__.py
myocr/modeling/backbones/mlp.py
myocr/modeling/backbones/mobilenet.py
myocr/modeling/backbones/restnet.py
myocr/modeling/backbones/svtrnet.py
myocr/modeling/configs/cls_mv3.yaml
myocr/modeling/configs/mlp.yaml
myocr/modeling/heads/__init__.py
myocr/modeling/heads/att_head.py
myocr/modeling/heads/cls_head.py
myocr/modeling/heads/ctc_head.py
myocr/modeling/heads/db_head.py
myocr/modeling/necks/__init__.py
myocr/modeling/necks/rnn.py
myocr/modeling/transforms/__init__.py
myocr/modeling/transforms/tps.py
myocr/pipelines/__init__.py
myocr/pipelines/common_ocr_pipeline.py
myocr/pipelines/document_ocr_pipeline.py
myocr/pipelines/structured_output_pipeline.py
myocr/pipelines/config/common_ocr_pipeline.yaml
myocr/pipelines/config/structured_output_pipeline.yaml
myocr/processors/__init__.py
myocr/processors/base.py
myocr/processors/img_classification_processor.py
myocr/processors/text_detection_processor.py
myocr/processors/text_direction_processor.py
myocr/processors/text_recognition_processor.py
myocr/training/base.py
myocr_kit-0.1.1.dist-info/licenses/LICENSE
myocr_kit-0.1.1.dist-info/METADATA
myocr_kit-0.1.1.dist-info/WHEEL
myocr_kit-0.1.1.dist-info/top_level.txt
myocr_kit-0.1.1.dist-info/RECORD
